breadcrumbs/__init__.py
breadcrumbs/base.py
breadcrumbs/configurations.py
breadcrumbs/log_formatters.py
pybreadcrumbs-0.0.2.dist-info/LICENSE
pybreadcrumbs-0.0.2.dist-info/METADATA
pybreadcrumbs-0.0.2.dist-info/WHEEL
pybreadcrumbs-0.0.2.dist-info/top_level.txt
pybreadcrumbs-0.0.2.dist-info/RECORD
