Metadata-Version: 2.1
Name: pybreadcrumbs
Version: 0.0.2
Summary: A lighweight functional tracer and log enhancer
Home-page: https://github.com/gofynd/pybreadcrumbs
Author: Hitesh Jha
Author-email: hitesh4official@gmail.com
License: UNKNOWN
Platform: UNKNOWN
Classifier: Programming Language :: Python :: 3
Classifier: License :: OSI Approved :: MIT License
Classifier: Operating System :: OS Independent
Requires-Python: >=3.7
Requires-Dist: ujson
